{
  "name": "libmedia",
  "entryPoints": [
    "packages/avplayer/src/AVPlayer.ts",
    "packages/ui/avplayer/src/AVPlayer.ts",
    "packages/avtranscoder/src/AVTranscoder.ts",

    "packages/avformat/src/index.ts",
    "packages/avcodec/src/index.ts",
    "packages/avnetwork/src/index.ts",
    "packages/avrender/src/index.ts",
    "packages/avfilter/src/index.ts",
    "packages/avpipeline/src/index.ts",
    "packages/avutil/src/index.ts",
    "packages/common/src/index.ts",
    "packages/common/src/io/index.ts",
    "packages/common/src/network/index.ts",
    "packages/common/src/math/index.ts",
    "packages/cheap/src/index.ts",
    "packages/videoscale/src/index.ts",
    "packages/audioresample/src/index.ts",
    "packages/audiostretchpitch/src/index.ts"
  ],
  "plugin": ["typedoc-plugin-rename-defaults"],
  "readme": "none",
  "out": "./docs/libmedia_api",
  "excludeInternal": true,
  "excludePrivate": true,
  "excludeProtected": true,
  "exclude": []
}